mycalc/calculator.py
yummongi-0.0.1.dist-info/METADATA
yummongi-0.0.1.dist-info/WHEEL
yummongi-0.0.1.dist-info/top_level.txt
yummongi-0.0.1.dist-info/RECORD
